{
  "schema_version": "1.0",
  "seed": 70005,
  "generated_at": "2026-05-04T23:24:39+00:00",
  "doc_type": "acord_25",
  "doc": {
    "format": "pdf",
    "scan_level": "digital",
    "strings": [
      "ACORD",
      "\u00ae",
      "CERTIFICATE OF LIABILITY INSURANCE",
      "DATE (MM/DD/YYYY)",
      "03/16/2026",
      "THIS CERTIFICATE IS ISSUED AS A MATTER OF INFORMATION ONLY AND CONFERS NO RIGHTS UPON THE CERTIFICATE HOLDER. THIS CERTIFICATE DOES NOT AFFIRMATIVELY OR NEGATIVELY AMEND, EXTEND OR ALTER THE COVERAGE AFFORDED BY THE POLICIES BELOW. THIS CERTIFICATE OF INSURANCE DOES NOT CONSTITUTE A CONTRACT BETWEEN THE ISSUING INSURER(S), AUTHORIZED REPRESENTATIVE OR PRODUCER, AND THE CERTIFICATE HOLDER.",
      "IMPORTANT:",
      "If the certificate holder is an ADDITIONAL INSURED, the policy(ies) must have ADDITIONAL INSURED provisions or be endorsed. If SUBROGATION IS WAIVED, subject to the terms and conditions of the policy, certain policies may require an endorsement. A statement on this certificate does not confer rights to the certificate holder in lieu of such endorsement(s).",
      "PRODUCER",
      "Transportation Insurance Specialists",
      "David Reinhardt",
      "41 South High Street, Suite 2800",
      "Columbus, OH 43215",
      "Phone: (614) 555-0493  Fax: (614) 267-6839",
      "E-Mail: dreinhardt@tisgroup.com",
      "INSURED",
      "Great Lakes Freight Systems, Incorporated",
      "1200 Nationwide Blvd.",
      "CONTACT NAME:",
      "PHONE (A/C, No, Ext):",
      "(614) 555-0493",
      "FAX (A/C, No):",
      "(614) 267-6839",
      "E-MAIL ADDRESS:",
      "dreinhardt@tisgroup.com",
      "INSURER(S) AFFORDING COVERAGE",
      "NAIC #",
      "INSURER A:",
      "Ohio Bureau of Workers' Compensation",
      "21008",
      "INSURER B:",
      "Standard Insurance Company",
      "21093",
      "INSURER C:",
      "21088",
      "INSURER D:",
      "21206",
      "INSURER E:",
      "INSURER F:",
      "COVERAGES",
      "CERTIFICATE NUMBER:",
      "REVISION NUMBER:",
      "THIS IS TO CERTIFY THAT THE POLICIES OF INSURANCE LISTED BELOW HAVE BEEN ISSUED TO THE INSURED NAMED ABOVE FOR THE POLICY PERIOD INDICATED. NOTWITHSTANDING ANY REQUIREMENT, TERM OR CONDITION OF ANY CONTRACT OR OTHER DOCUMENT WITH RESPECT TO WHICH THIS CERTIFICATE MAY BE ISSUED OR MAY PERTAIN, THE INSURANCE AFFORDED BY THE POLICIES DESCRIBED HEREIN IS SUBJECT TO ALL THE TERMS, EXCLUSIONS AND CONDITIONS OF SUCH POLICIES. LIMITS SHOWN MAY HAVE BEEN REDUCED BY PAID CLAIMS.",
      "INSR",
      "LTR",
      "TYPE OF INSURANCE",
      "ADDL  SUBR",
      "INSD  WVD",
      "POLICY NUMBER",
      "POLICY EFF",
      "(MM/DD/YYYY)",
      "POLICY EXP",
      "LIMITS",
      "B",
      "COMMERCIAL GENERAL LIABILITY",
      "CLAIMS-MADE",
      "X",
      "OCCUR",
      "GEN'L AGGREGATE LIMIT APPLIES PER:",
      "POLICY",
      "PRO-JECT",
      "LOC",
      "Y",
      "gl GLFS 2025 8821",
      "06/01/2025",
      "06/01/2026",
      "EACH OCCURRENCE",
      "$ 2,000,000",
      "DAMAGE TO RENTED PREMISES (Ea occurrence)",
      "$ 500,000",
      "MED EXP (Any one person)",
      "$ 5,000",
      "PERSONAL & ADV INJURY",
      "GENERAL AGGREGATE",
      "$ 4,000,000",
      "PRODUCTS - COMP/OP AGG",
      "$",
      "C",
      "AUTOMOBILE LIABILITY",
      "ANY AUTO",
      "OWNED AUTOS ONLY",
      "SCHEDULED AUTOS",
      "HIRED AUTOS ONLY",
      "NON-OWNED AUTOS ONLY",
      "CAGLFS20258822",
      "COMBINED SINGLE LIMIT (Ea accident)",
      "$ 5,000,000",
      "BODILY INJURY (Per person)",
      "BODILY INJURY (Per accident)",
      "PROPERTY DAMAGE (Per accident)",
      "D",
      "UMBRELLA LIAB",
      "DED    RETENTION $",
      "SIC CU025454",
      "$ 10,000,000",
      "AGGREGATE",
      "A",
      "WORKERS COMPENSATION",
      "AND EMPLOYERS' LIABILITY",
      "ANY PROPRIETOR/PARTNER/EXECUTIVE",
      "OFFICER/MEMBER EXCLUDED?",
      "N / A",
      "(Mandatory in NH)",
      "WC GLFS 2025 8820",
      "WC STATU-",
      "TORY LIMITS",
      "OTH-",
      "ER",
      "E.L. EACH ACCIDENT",
      "E.L. DISEASE - EA EMPLOYEE",
      "E.L. DISEASE - POLICY LIMIT",
      "DESCRIPTION OF OPERATIONS / LOCATIONS / VEHICLES  (ACORD 101, Additional Remarks Schedule, may be attached if more space is required)",
      "RE: Regional trucking and freight logistics \u2014 LTL and FTL general freight, warehousing and distribution services across the Midwest and Mid-Atlantic corridors\nLocations: Corporate Headquarters & Main Terminal - 1200 Nationwide Boulevard, Columbus, OH 43215; Rickenbacker Air Hub - 2500 Norton Road, Columbus, OH 43217; Cleveland Distribution Center - 6000 Rockside Woods Boulevard, Independence, OH 44131\nQuantum Realty Management Inc. is included as Additional Insured as required by written contract. 30 days notice of cancellation will be provided.",
      "RE: Regional trucking and freight logistics \u2014 LTL and FTL general freight, warehousing and distribution services across the Midwest and Mid-Atlantic corridors",
      "Locations: Corporate Headquarters & Main Terminal - 1200 Nationwide Boulevard, Columbus, OH 43215; Rickenbacker Air Hub - 2500 Norton Road, Columbus,",
      "OH 43217; Cleveland Distribution Center - 6000 Rockside Woods Boulevard, Independence, OH 44131 Quantum Realty Management Inc. is included as Additional",
      "Insured as required by written contract. 30 days notice of cancellation will be provided.",
      "CERTIFICATE HOLDER",
      "CANCELLATION",
      "Quantum Realty Management Inc.",
      "5158 Summit Avenue",
      "Little Rock, AR 72201",
      "SHOULD ANY OF THE ABOVE DESCRIBED POLICIES BE CANCELLED BEFORE THE EXPIRATION DATE THEREOF, NOTICE WILL BE DELIVERED IN ACCORDANCE WITH THE POLICY PROVISIONS.",
      "AUTHORIZED REPRESENTATIVE",
      "Margaret Sullivan",
      "ACORD 25 (2016/03)",
      "\u00a9 1988-2016 ACORD CORPORATION. All rights reserved.",
      "The ACORD name and logo are registered marks of ACORD",
      "Page 1 of 1",
      "M. Johnson",
      "6/18/2025",
      "Need docs"
    ],
    "numbers": [
      2026,
      2800,
      43215,
      614,
      555,
      493,
      267,
      6839,
      1200,
      21008,
      21093,
      21088,
      21206,
      2025,
      8821,
      2000000,
      500000,
      5000,
      4000000,
      20258822,
      5000000,
      25454,
      10000000,
      8820,
      101,
      2500,
      43217,
      6000,
      44131,
      5158,
      72201,
      2016,
      1988
    ],
    "tokens": [
      "acord",
      "certificate",
      "of",
      "liability",
      "insurance",
      "date",
      "mm",
      "dd",
      "yyyy",
      "03",
      "16",
      "2026",
      "this",
      "is",
      "issued",
      "as",
      "matter",
      "information",
      "only",
      "and",
      "confers",
      "no",
      "rights",
      "upon",
      "the",
      "holder",
      "does",
      "not",
      "affirmatively",
      "or",
      "negatively",
      "amend",
      "extend",
      "alter",
      "coverage",
      "afforded",
      "by",
      "policies",
      "below",
      "constitute",
      "contract",
      "between",
      "issuing",
      "insurer",
      "authorized",
      "representative",
      "producer",
      "important",
      "if",
      "an",
      "additional",
      "insured",
      "policy",
      "ies",
      "must",
      "have",
      "provisions",
      "be",
      "endorsed",
      "subrogation",
      "waived",
      "subject",
      "to",
      "terms",
      "conditions",
      "certain",
      "may",
      "require",
      "endorsement",
      "statement",
      "on",
      "confer",
      "in",
      "lieu",
      "such",
      "transportation",
      "specialists",
      "david",
      "reinhardt",
      "41",
      "south",
      "high",
      "street",
      "suite",
      "2800",
      "columbus",
      "oh",
      "43215",
      "phone",
      "614",
      "555-0493",
      "fax",
      "267-6839",
      "e-mail",
      "dreinhardt",
      "tisgroup.com",
      "great",
      "lakes",
      "freight",
      "systems",
      "incorporated",
      "1200",
      "nationwide",
      "blvd",
      "contact",
      "name",
      "ext",
      "address",
      "affording",
      "naic",
      "ohio",
      "bureau",
      "workers",
      "compensation",
      "21008",
      "standard",
      "company",
      "21093",
      "21088",
      "21206",
      "coverages",
      "number",
      "revision",
      "certify",
      "that",
      "listed",
      "been",
      "named",
      "above",
      "for",
      "period",
      "indicated",
      "notwithstanding",
      "any",
      "requirement",
      "term",
      "condition",
      "other",
      "document",
      "with",
      "respect",
      "which",
      "pertain",
      "described",
      "herein",
      "all",
      "exclusions",
      "limits",
      "shown",
      "reduced",
      "paid",
      "claims",
      "insr",
      "ltr",
      "type",
      "addl",
      "subr",
      "insd",
      "wvd",
      "eff",
      "exp",
      "commercial",
      "general",
      "claims-made",
      "occur",
      "gen",
      "aggregate",
      "limit",
      "applies",
      "per",
      "pro-ject",
      "loc",
      "gl",
      "glfs",
      "2025",
      "8821",
      "06",
      "01",
      "each",
      "occurrence",
      "000",
      "damage",
      "rented",
      "premises",
      "ea",
      "500",
      "med",
      "one",
      "person",
      "personal",
      "adv",
      "injury",
      "products",
      "comp",
      "op",
      "agg",
      "automobile",
      "auto",
      "owned",
      "autos",
      "scheduled",
      "hired",
      "non-owned",
      "caglfs20258822",
      "combined",
      "single",
      "accident",
      "bodily",
      "property",
      "umbrella",
      "liab",
      "ded",
      "retention",
      "sic",
      "cu025454",
      "10",
      "employers",
      "proprietor",
      "partner",
      "executive",
      "officer",
      "member",
      "excluded",
      "mandatory",
      "nh",
      "wc",
      "8820",
      "statu",
      "tory",
      "oth",
      "er",
      "e.l",
      "disease",
      "employee",
      "description",
      "operations",
      "locations",
      "vehicles",
      "101",
      "remarks",
      "schedule",
      "attached",
      "more",
      "space",
      "required",
      "re",
      "regional",
      "trucking",
      "logistics",
      "ltl",
      "ftl",
      "warehousing",
      "distribution",
      "services",
      "across",
      "midwest",
      "mid-atlantic",
      "corridors",
      "corporate",
      "headquarters",
      "main",
      "terminal",
      "boulevard",
      "rickenbacker",
      "air",
      "hub",
      "2500",
      "norton",
      "road",
      "43217",
      "cleveland",
      "center",
      "6000",
      "rockside",
      "woods",
      "independence",
      "44131",
      "quantum",
      "realty",
      "management",
      "inc",
      "included",
      "written",
      "30",
      "days",
      "notice",
      "cancellation",
      "will",
      "provided",
      "5158",
      "summit",
      "avenue",
      "little",
      "rock",
      "ar",
      "72201",
      "should",
      "cancelled",
      "before",
      "expiration",
      "thereof",
      "delivered",
      "accordance",
      "margaret",
      "sullivan",
      "25",
      "2016",
      "1988-2016",
      "corporation",
      "reserved",
      "logo",
      "are",
      "registered",
      "marks",
      "page",
      "johnson",
      "18",
      "need",
      "docs"
    ],
    "rendered_text": "\f",
    "elements": [
      {
        "value": "ACORD",
        "kind": "string",
        "origin": "canvas.drawString",
        "page": 1,
        "x": 20.0,
        "y": 762.0
      },
      {
        "value": "\u00ae",
        "kind": "string",
        "origin": "canvas.drawString",
        "page": 1,
        "x": 74.0,
        "y": 768.0
      },
      {
        "value": "CERTIFICATE OF LIABILITY INSURANCE",
        "kind": "string",
        "origin": "canvas.drawCentredString",
        "page": 1,
        "x": 306.0,
        "y": 764.0
      },
      {
        "value": "DATE (MM/DD/YYYY)",
        "kind": "string",
        "origin": "canvas.drawString",
        "page": 1,
        "x": 496.0,
        "y": 770.0
      },
      {
        "value": "03/16/2026",
        "kind": "string",
        "origin": "canvas.drawString",
        "page": 1,
        "x": 496.0,
        "y": 760.0
      },
      {
        "value": "THIS CERTIFICATE IS ISSUED AS A MATTER OF INFORMATION ONLY AND CONFERS NO RIGHTS UPON THE CERTIFICATE HOLDER. THIS CERTIFICATE DOES NOT AFFIRMATIVELY OR NEGATIVELY AMEND, EXTEND OR ALTER THE COVERAGE AFFORDED BY THE POLICIES BELOW. THIS CERTIFICATE OF INSURANCE DOES NOT CONSTITUTE A CONTRACT BETWEEN THE ISSUING INSURER(S), AUTHORIZED REPRESENTATIVE OR PRODUCER, AND THE CERTIFICATE HOLDER.",
        "kind": "string",
        "origin": "acord_renderer.wrapped_text",
        "page": 1,
        "x": 20.0,
        "y": 49.0
      },
      {
        "value": "THIS CERTIFICATE IS ISSUED AS A MATTER OF INFORMATION ONLY AND CONFERS NO RIGHTS UPON THE CERTIFICATE HOLDER. THIS CERTIFICATE DOES NOT AFFIRMATIVELY OR NEGATIVELY AMEND, EXTEND OR ALTER THE COVERAGE AFFORDED BY THE POLICIES BELOW. THIS CERTIFICATE OF INSURANCE DOES NOT CONSTITUTE A CONTRACT BETWEEN THE ISSUING INSURER(S), AUTHORIZED REPRESENTATIVE OR PRODUCER, AND THE CERTIFICATE HOLDER.",
        "kind": "string",
        "origin": "reportlab.paragraph",
        "page": 1,
        "x": 20.0,
        "y": 723.5
      },
      {
        "value": "IMPORTANT:",
        "kind": "string",
        "origin": "canvas.drawString",
        "page": 1,
        "x": 20.0,
        "y": 716.0
      },
      {
        "value": "If the certificate holder is an ADDITIONAL INSURED, the policy(ies) must have ADDITIONAL INSURED provisions or be endorsed. If SUBROGATION IS WAIVED, subject to the terms and conditions of the policy, certain policies may require an endorsement. A statement on this certificate does not confer rights to the certificate holder in lieu of such endorsement(s).",
        "kind": "string",
        "origin": "acord_renderer.wrapped_text",
        "page": 1,
        "x": 70.0,
        "y": 71.5
      },
      {
        "value": "If the certificate holder is an ADDITIONAL INSURED, the policy(ies) must have ADDITIONAL INSURED provisions or be endorsed. If SUBROGATION IS WAIVED, subject to the terms and conditions of the policy, certain policies may require an endorsement. A statement on this certificate does not confer rights to the certificate holder in lieu of such endorsement(s).",
        "kind": "string",
        "origin": "reportlab.paragraph",
        "page": 1,
        "x": 70.0,
        "y": 707.5
      },
      {
        "value": "PRODUCER",
        "kind": "string",
        "origin": "canvas.drawString",
        "page": 1,
        "x": 22.0,
        "y": 699.0
      },
      {
        "value": "Transportation Insurance Specialists",
        "kind": "string",
        "origin": "canvas.drawString",
        "page": 1,
        "x": 22.0,
        "y": 688.0
      },
      {
        "value": "David Reinhardt",
        "kind": "string",
        "origin": "canvas.drawString",
        "page": 1,
        "x": 22.0,
        "y": 678.5
      },
      {
        "value": "41 South High Street, Suite 2800",
        "kind": "string",
        "origin": "canvas.drawString",
        "page": 1,
        "x": 22.0,
        "y": 669.0
      },
      {
        "value": "Columbus, OH 43215",
        "kind": "string",
        "origin": "canvas.drawString",
        "page": 1,
        "x": 22.0,
        "y": 659.5
      },
      {
        "value": "Phone: (614) 555-0493  Fax: (614) 267-6839",
        "kind": "string",
        "origin": "canvas.drawString",
        "page": 1,
        "x": 22.0,
        "y": 650.0
      },
      {
        "value": "E-Mail: dreinhardt@tisgroup.com",
        "kind": "string",
        "origin": "canvas.drawString",
        "page": 1,
        "x": 22.0,
        "y": 640.5
      },
      {
        "value": "INSURED",
        "kind": "string",
        "origin": "canvas.drawString",
        "page": 1,
        "x": 22.0,
        "y": 629.0
      },
      {
        "value": "Great Lakes Freight Systems, Incorporated",
        "kind": "string",
        "origin": "canvas.drawString",
        "page": 1,
        "x": 22.0,
        "y": 618.0
      },
      {
        "value": "1200 Nationwide Blvd.",
        "kind": "string",
        "origin": "canvas.drawString",
        "page": 1,
        "x": 22.0,
        "y": 608.0
      },
      {
        "value": "Columbus, OH 43215",
        "kind": "string",
        "origin": "canvas.drawString",
        "page": 1,
        "x": 22.0,
        "y": 598.0
      },
      {
        "value": "CONTACT NAME:",
        "kind": "string",
        "origin": "canvas.drawString",
        "page": 1,
        "x": 336.8,
        "y": 699.0
      },
      {
        "value": "David Reinhardt",
        "kind": "string",
        "origin": "canvas.drawString",
        "page": 1,
        "x": 336.8,
        "y": 690.0
      },
      {
        "value": "PHONE (A/C, No, Ext):",
        "kind": "string",
        "origin": "canvas.drawString",
        "page": 1,
        "x": 336.8,
        "y": 683.0
      },
      {
        "value": "(614) 555-0493",
        "kind": "string",
        "origin": "canvas.drawString",
        "page": 1,
        "x": 336.8,
        "y": 674.0
      },
      {
        "value": "FAX (A/C, No):",
        "kind": "string",
        "origin": "canvas.drawString",
        "page": 1,
        "x": 336.8,
        "y": 667.0
      },
      {
        "value": "(614) 267-6839",
        "kind": "string",
        "origin": "canvas.drawString",
        "page": 1,
        "x": 336.8,
        "y": 658.0
      },
      {
        "value": "E-MAIL ADDRESS:",
        "kind": "string",
        "origin": "canvas.drawString",
        "page": 1,
        "x": 336.8,
        "y": 651.0
      },
      {
        "value": "dreinhardt@tisgroup.com",
        "kind": "string",
        "origin": "canvas.drawString",
        "page": 1,
        "x": 336.8,
        "y": 642.0
      },
      {
        "value": "INSURER(S) AFFORDING COVERAGE",
        "kind": "string",
        "origin": "canvas.drawString",
        "page": 1,
        "x": 338.8,
        "y": 633.0
      },
      {
        "value": "NAIC #",
        "kind": "string",
        "origin": "canvas.drawRightString",
        "page": 1,
        "x": 564.0,
        "y": 633.0
      },
      {
        "value": "INSURER A:",
        "kind": "string",
        "origin": "canvas.drawString",
        "page": 1,
        "x": 338.8,
        "y": 622.5
      },
      {
        "value": "Ohio Bureau of Workers' Compensation",
        "kind": "string",
        "origin": "canvas.drawString",
        "page": 1,
        "x": 394.8,
        "y": 622.5
      },
      {
        "value": "21008",
        "kind": "string",
        "origin": "canvas.drawRightString",
        "page": 1,
        "x": 590.0,
        "y": 622.5
      },
      {
        "value": "INSURER B:",
        "kind": "string",
        "origin": "canvas.drawString",
        "page": 1,
        "x": 338.8,
        "y": 611.5
      },
      {
        "value": "Standard Insurance Company",
        "kind": "string",
        "origin": "canvas.drawString",
        "page": 1,
        "x": 394.8,
        "y": 611.5
      },
      {
        "value": "21093",
        "kind": "string",
        "origin": "canvas.drawRightString",
        "page": 1,
        "x": 590.0,
        "y": 611.5
      },
      {
        "value": "INSURER C:",
        "kind": "string",
        "origin": "canvas.drawString",
        "page": 1,
        "x": 338.8,
        "y": 600.5
      },
      {
        "value": "Standard Insurance Company",
        "kind": "string",
        "origin": "canvas.drawString",
        "page": 1,
        "x": 394.8,
        "y": 600.5
      },
      {
        "value": "21088",
        "kind": "string",
        "origin": "canvas.drawRightString",
        "page": 1,
        "x": 590.0,
        "y": 600.5
      },
      {
        "value": "INSURER D:",
        "kind": "string",
        "origin": "canvas.drawString",
        "page": 1,
        "x": 338.8,
        "y": 589.5
      },
      {
        "value": "Standard Insurance Company",
        "kind": "string",
        "origin": "canvas.drawString",
        "page": 1,
        "x": 394.8,
        "y": 589.5
      },
      {
        "value": "21206",
        "kind": "string",
        "origin": "canvas.drawRightString",
        "page": 1,
        "x": 590.0,
        "y": 589.5
      },
      {
        "value": "INSURER E:",
        "kind": "string",
        "origin": "canvas.drawString",
        "page": 1,
        "x": 338.8,
        "y": 578.5
      },
      {
        "value": "INSURER F:",
        "kind": "string",
        "origin": "canvas.drawString",
        "page": 1,
        "x": 338.8,
        "y": 567.5
      },
      {
        "value": "COVERAGES",
        "kind": "string",
        "origin": "canvas.drawString",
        "page": 1,
        "x": 22.0,
        "y": 549.5
      },
      {
        "value": "CERTIFICATE NUMBER:",
        "kind": "string",
        "origin": "canvas.drawString",
        "page": 1,
        "x": 308.0,
        "y": 553.5
      },
      {
        "value": "REVISION NUMBER:",
        "kind": "string",
        "origin": "canvas.drawString",
        "page": 1,
        "x": 452.0,
        "y": 553.5
      },
      {
        "value": "THIS IS TO CERTIFY THAT THE POLICIES OF INSURANCE LISTED BELOW HAVE BEEN ISSUED TO THE INSURED NAMED ABOVE FOR THE POLICY PERIOD INDICATED. NOTWITHSTANDING ANY REQUIREMENT, TERM OR CONDITION OF ANY CONTRACT OR OTHER DOCUMENT WITH RESPECT TO WHICH THIS CERTIFICATE MAY BE ISSUED OR MAY PERTAIN, THE INSURANCE AFFORDED BY THE POLICIES DESCRIBED HEREIN IS SUBJECT TO ALL THE TERMS, EXCLUSIONS AND CONDITIONS OF SUCH POLICIES. LIMITS SHOWN MAY HAVE BEEN REDUCED BY PAID CLAIMS.",
        "kind": "string",
        "origin": "acord_renderer.wrapped_text",
        "page": 1,
        "x": 20.0,
        "y": 247.5
      },
      {
        "value": "THIS IS TO CERTIFY THAT THE POLICIES OF INSURANCE LISTED BELOW HAVE BEEN ISSUED TO THE INSURED NAMED ABOVE FOR THE POLICY PERIOD INDICATED. NOTWITHSTANDING ANY REQUIREMENT, TERM OR CONDITION OF ANY CONTRACT OR OTHER DOCUMENT WITH RESPECT TO WHICH THIS CERTIFICATE MAY BE ISSUED OR MAY PERTAIN, THE INSURANCE AFFORDED BY THE POLICIES DESCRIBED HEREIN IS SUBJECT TO ALL THE TERMS, EXCLUSIONS AND CONDITIONS OF SUCH POLICIES. LIMITS SHOWN MAY HAVE BEEN REDUCED BY PAID CLAIMS.",
        "kind": "string",
        "origin": "reportlab.paragraph",
        "page": 1,
        "x": 20.0,
        "y": 528.0
      },
      {
        "value": "INSR",
        "kind": "string",
        "origin": "canvas.drawString",
        "page": 1,
        "x": 20.0,
        "y": 518.0
      },
      {
        "value": "LTR",
        "kind": "string",
        "origin": "canvas.drawString",
        "page": 1,
        "x": 20.0,
        "y": 511.5
      },
      {
        "value": "TYPE OF INSURANCE",
        "kind": "string",
        "origin": "canvas.drawString",
        "page": 1,
        "x": 43.04,
        "y": 518.0
      },
      {
        "value": "ADDL  SUBR",
        "kind": "string",
        "origin": "canvas.drawString",
        "page": 1,
        "x": 164.0,
        "y": 518.0
      },
      {
        "value": "INSD  WVD",
        "kind": "string",
        "origin": "canvas.drawString",
        "page": 1,
        "x": 164.0,
        "y": 511.5
      },
      {
        "value": "POLICY NUMBER",
        "kind": "string",
        "origin": "canvas.drawString",
        "page": 1,
        "x": 198.56,
        "y": 518.0
      },
      {
        "value": "POLICY EFF",
        "kind": "string",
        "origin": "canvas.drawString",
        "page": 1,
        "x": 284.96,
        "y": 518.0
      },
      {
        "value": "(MM/DD/YYYY)",
        "kind": "string",
        "origin": "canvas.drawString",
        "page": 1,
        "x": 284.96,
        "y": 511.5
      },
      {
        "value": "POLICY EXP",
        "kind": "string",
        "origin": "canvas.drawString",
        "page": 1,
        "x": 336.8,
        "y": 518.0
      },
      {
        "value": "(MM/DD/YYYY)",
        "kind": "string",
        "origin": "canvas.drawString",
        "page": 1,
        "x": 336.8,
        "y": 511.5
      },
      {
        "value": "LIMITS",
        "kind": "string",
        "origin": "canvas.drawString",
        "page": 1,
        "x": 388.64,
        "y": 518.0
      },
      {
        "value": "B",
        "kind": "string",
        "origin": "canvas.drawCentredString",
        "page": 1,
        "x": 29.52,
        "y": 497.0
      },
      {
        "value": "COMMERCIAL GENERAL LIABILITY",
        "kind": "string",
        "origin": "canvas.drawString",
        "page": 1,
        "x": 45.04,
        "y": 498.0
      },
      {
        "value": "CLAIMS-MADE",
        "kind": "string",
        "origin": "canvas.drawString",
        "page": 1,
        "x": 56.04,
        "y": 489.0
      },
      {
        "value": "X",
        "kind": "string",
        "origin": "canvas.drawCentredString",
        "page": 1,
        "x": 96.315,
        "y": 489.2
      },
      {
        "value": "OCCUR",
        "kind": "string",
        "origin": "canvas.drawString",
        "page": 1,
        "x": 102.315,
        "y": 489.0
      },
      {
        "value": "GEN'L AGGREGATE LIMIT APPLIES PER:",
        "kind": "string",
        "origin": "canvas.drawString",
        "page": 1,
        "x": 45.04,
        "y": 478.5
      },
      {
        "value": "X",
        "kind": "string",
        "origin": "canvas.drawCentredString",
        "page": 1,
        "x": 50.04,
        "y": 471.2
      },
      {
        "value": "POLICY",
        "kind": "string",
        "origin": "canvas.drawString",
        "page": 1,
        "x": 56.04,
        "y": 471.0
      },
      {
        "value": "PRO-JECT",
        "kind": "string",
        "origin": "canvas.drawString",
        "page": 1,
        "x": 87.19,
        "y": 471.0
      },
      {
        "value": "LOC",
        "kind": "string",
        "origin": "canvas.drawString",
        "page": 1,
        "x": 124.39,
        "y": 471.0
      },
      {
        "value": "Y",
        "kind": "string",
        "origin": "canvas.drawCentredString",
        "page": 1,
        "x": 179.28,
        "y": 467.0
      },
      {
        "value": "Y",
        "kind": "string",
        "origin": "canvas.drawCentredString",
        "page": 1,
        "x": 179.28,
        "y": 457.0
      },
      {
        "value": "gl GLFS 2025 8821",
        "kind": "string",
        "origin": "canvas.drawString",
        "page": 1,
        "x": 200.56,
        "y": 465.0
      },
      {
        "value": "06/01/2025",
        "kind": "string",
        "origin": "canvas.drawString",
        "page": 1,
        "x": 286.96,
        "y": 465.0
      },
      {
        "value": "06/01/2026",
        "kind": "string",
        "origin": "canvas.drawString",
        "page": 1,
        "x": 338.8,
        "y": 465.0
      },
      {
        "value": "EACH OCCURRENCE",
        "kind": "string",
        "origin": "acord_renderer.wrapped_text",
        "page": 1,
        "x": 388.64,
        "y": 287.0
      },
      {
        "value": "EACH OCCURRENCE",
        "kind": "string",
        "origin": "reportlab.paragraph",
        "page": 1,
        "x": 388.64,
        "y": 498.675
      },
      {
        "value": "$ 2,000,000",
        "kind": "string",
        "origin": "canvas.drawRightString",
        "page": 1,
        "x": 592.0,
        "y": 497.5
      },
      {
        "value": "DAMAGE TO RENTED PREMISES (Ea occurrence)",
        "kind": "string",
        "origin": "acord_renderer.wrapped_text",
        "page": 1,
        "x": 388.64,
        "y": 299.0
      },
      {
        "value": "DAMAGE TO RENTED PREMISES (Ea occurrence)",
        "kind": "string",
        "origin": "reportlab.paragraph",
        "page": 1,
        "x": 388.64,
        "y": 480.35
      },
      {
        "value": "$ 500,000",
        "kind": "string",
        "origin": "canvas.drawRightString",
        "page": 1,
        "x": 592.0,
        "y": 485.5
      },
      {
        "value": "MED EXP (Any one person)",
        "kind": "string",
        "origin": "acord_renderer.wrapped_text",
        "page": 1,
        "x": 388.64,
        "y": 311.0
      },
      {
        "value": "MED EXP (Any one person)",
        "kind": "string",
        "origin": "reportlab.paragraph",
        "page": 1,
        "x": 388.64,
        "y": 474.675
      },
      {
        "value": "$ 5,000",
        "kind": "string",
        "origin": "canvas.drawRightString",
        "page": 1,
        "x": 592.0,
        "y": 473.5
      },
      {
        "value": "PERSONAL & ADV INJURY",
        "kind": "string",
        "origin": "acord_renderer.wrapped_text",
        "page": 1,
        "x": 388.64,
        "y": 323.0
      },
      {
        "value": "PERSONAL & ADV INJURY",
        "kind": "string",
        "origin": "reportlab.paragraph.frag",
        "page": 1,
        "x": 388.64,
        "y": 462.675
      },
      {
        "value": "$ 2,000,000",
        "kind": "string",
        "origin": "canvas.drawRightString",
        "page": 1,
        "x": 592.0,
        "y": 461.5
      },
      {
        "value": "GENERAL AGGREGATE",
        "kind": "string",
        "origin": "acord_renderer.wrapped_text",
        "page": 1,
        "x": 388.64,
        "y": 335.0
      },
      {
        "value": "GENERAL AGGREGATE",
        "kind": "string",
        "origin": "reportlab.paragraph",
        "page": 1,
        "x": 388.64,
        "y": 450.675
      },
      {
        "value": "$ 4,000,000",
        "kind": "string",
        "origin": "canvas.drawRightString",
        "page": 1,
        "x": 592.0,
        "y": 449.5
      },
      {
        "value": "PRODUCTS - COMP/OP AGG",
        "kind": "string",
        "origin": "acord_renderer.wrapped_text",
        "page": 1,
        "x": 388.64,
        "y": 347.0
      },
      {
        "value": "PRODUCTS - COMP/OP AGG",
        "kind": "string",
        "origin": "reportlab.paragraph",
        "page": 1,
        "x": 388.64,
        "y": 438.675
      },
      {
        "value": "$ 4,000,000",
        "kind": "string",
        "origin": "canvas.drawRightString",
        "page": 1,
        "x": 592.0,
        "y": 437.5
      },
      {
        "value": "$",
        "kind": "string",
        "origin": "canvas.drawRightString",
        "page": 1,
        "x": 592.0,
        "y": 425.5
      },
      {
        "value": "C",
        "kind": "string",
        "origin": "canvas.drawCentredString",
        "page": 1,
        "x": 29.52,
        "y": 413.0
      },
      {
        "value": "AUTOMOBILE LIABILITY",
        "kind": "string",
        "origin": "canvas.drawString",
        "page": 1,
        "x": 45.04,
        "y": 414.0
      },
      {
        "value": "X",
        "kind": "string",
        "origin": "canvas.drawCentredString",
        "page": 1,
        "x": 50.04,
        "y": 405.2
      },
      {
        "value": "ANY AUTO",
        "kind": "string",
        "origin": "canvas.drawString",
        "page": 1,
        "x": 56.04,
        "y": 405.0
      },
      {
        "value": "OWNED AUTOS ONLY",
        "kind": "string",
        "origin": "canvas.drawString",
        "page": 1,
        "x": 56.04,
        "y": 395.0
      },
      {
        "value": "SCHEDULED AUTOS",
        "kind": "string",
        "origin": "canvas.drawString",
        "page": 1,
        "x": 117.44,
        "y": 395.0
      },
      {
        "value": "HIRED AUTOS ONLY",
        "kind": "string",
        "origin": "canvas.drawString",
        "page": 1,
        "x": 56.04,
        "y": 385.0
      },
      {
        "value": "NON-OWNED AUTOS ONLY",
        "kind": "string",
        "origin": "canvas.drawString",
        "page": 1,
        "x": 117.44,
        "y": 385.0
      },
      {
        "value": "Y",
        "kind": "string",
        "origin": "canvas.drawCentredString",
        "page": 1,
        "x": 179.28,
        "y": 395.0
      },
      {
        "value": "Y",
        "kind": "string",
        "origin": "canvas.drawCentredString",
        "page": 1,
        "x": 179.28,
        "y": 385.0
      },
      {
        "value": "CAGLFS20258822",
        "kind": "string",
        "origin": "canvas.drawString",
        "page": 1,
        "x": 200.56,
        "y": 393.0
      },
      {
        "value": "06/01/2025",
        "kind": "string",
        "origin": "canvas.drawString",
        "page": 1,
        "x": 286.96,
        "y": 393.0
      },
      {
        "value": "06/01/2026",
        "kind": "string",
        "origin": "canvas.drawString",
        "page": 1,
        "x": 338.8,
        "y": 393.0
      },
      {
        "value": "COMBINED SINGLE LIMIT (Ea accident)",
        "kind": "string",
        "origin": "acord_renderer.wrapped_text",
        "page": 1,
        "x": 388.64,
        "y": 371.0
      },
      {
        "value": "COMBINED SINGLE LIMIT (Ea accident)",
        "kind": "string",
        "origin": "reportlab.paragraph",
        "page": 1,
        "x": 388.64,
        "y": 414.675
      },
      {
        "value": "$ 5,000,000",
        "kind": "string",
        "origin": "canvas.drawRightString",
        "page": 1,
        "x": 592.0,
        "y": 413.5
      },
      {
        "value": "BODILY INJURY (Per person)",
        "kind": "string",
        "origin": "acord_renderer.wrapped_text",
        "page": 1,
        "x": 388.64,
        "y": 383.0
      },
      {
        "value": "BODILY INJURY (Per person)",
        "kind": "string",
        "origin": "reportlab.paragraph",
        "page": 1,
        "x": 388.64,
        "y": 402.675
      },
      {
        "value": "BODILY INJURY (Per accident)",
        "kind": "string",
        "origin": "acord_renderer.wrapped_text",
        "page": 1,
        "x": 388.64,
        "y": 395.0
      },
      {
        "value": "BODILY INJURY (Per accident)",
        "kind": "string",
        "origin": "reportlab.paragraph",
        "page": 1,
        "x": 388.64,
        "y": 390.675
      },
      {
        "value": "PROPERTY DAMAGE (Per accident)",
        "kind": "string",
        "origin": "acord_renderer.wrapped_text",
        "page": 1,
        "x": 388.64,
        "y": 407.0
      },
      {
        "value": "PROPERTY DAMAGE (Per accident)",
        "kind": "string",
        "origin": "reportlab.paragraph",
        "page": 1,
        "x": 388.64,
        "y": 378.675
      },
      {
        "value": "$",
        "kind": "string",
        "origin": "canvas.drawRightString",
        "page": 1,
        "x": 592.0,
        "y": 365.5
      },
      {
        "value": "D",
        "kind": "string",
        "origin": "canvas.drawCentredString",
        "page": 1,
        "x": 29.52,
        "y": 353.0
      },
      {
        "value": "UMBRELLA LIAB",
        "kind": "string",
        "origin": "canvas.drawString",
        "page": 1,
        "x": 45.04,
        "y": 354.0
      },
      {
        "value": "X",
        "kind": "string",
        "origin": "canvas.drawCentredString",
        "page": 1,
        "x": 50.04,
        "y": 345.2
      },
      {
        "value": "OCCUR",
        "kind": "string",
        "origin": "canvas.drawString",
        "page": 1,
        "x": 56.04,
        "y": 345.0
      },
      {
        "value": "CLAIMS-MADE",
        "kind": "string",
        "origin": "canvas.drawString",
        "page": 1,
        "x": 84.165,
        "y": 345.0
      },
      {
        "value": "DED    RETENTION $",
        "kind": "string",
        "origin": "canvas.drawString",
        "page": 1,
        "x": 45.04,
        "y": 334.5
      },
      {
        "value": "Y",
        "kind": "string",
        "origin": "canvas.drawCentredString",
        "page": 1,
        "x": 179.28,
        "y": 341.0
      },
      {
        "value": "Y",
        "kind": "string",
        "origin": "canvas.drawCentredString",
        "page": 1,
        "x": 179.28,
        "y": 331.0
      },
      {
        "value": "SIC CU025454",
        "kind": "string",
        "origin": "canvas.drawString",
        "page": 1,
        "x": 200.56,
        "y": 339.0
      },
      {
        "value": "06/01/2025",
        "kind": "string",
        "origin": "canvas.drawString",
        "page": 1,
        "x": 286.96,
        "y": 339.0
      },
      {
        "value": "06/01/2026",
        "kind": "string",
        "origin": "canvas.drawString",
        "page": 1,
        "x": 338.8,
        "y": 339.0
      },
      {
        "value": "EACH OCCURRENCE",
        "kind": "string",
        "origin": "acord_renderer.wrapped_text",
        "page": 1,
        "x": 388.64,
        "y": 431.0
      },
      {
        "value": "EACH OCCURRENCE",
        "kind": "string",
        "origin": "reportlab.paragraph",
        "page": 1,
        "x": 388.64,
        "y": 354.675
      },
      {
        "value": "$ 10,000,000",
        "kind": "string",
        "origin": "canvas.drawRightString",
        "page": 1,
        "x": 592.0,
        "y": 353.5
      },
      {
        "value": "AGGREGATE",
        "kind": "string",
        "origin": "acord_renderer.wrapped_text",
        "page": 1,
        "x": 388.64,
        "y": 443.0
      },
      {
        "value": "AGGREGATE",
        "kind": "string",
        "origin": "reportlab.paragraph",
        "page": 1,
        "x": 388.64,
        "y": 342.675
      },
      {
        "value": "$ 10,000,000",
        "kind": "string",
        "origin": "canvas.drawRightString",
        "page": 1,
        "x": 592.0,
        "y": 341.5
      },
      {
        "value": "$",
        "kind": "string",
        "origin": "canvas.drawRightString",
        "page": 1,
        "x": 592.0,
        "y": 329.5
      },
      {
        "value": "A",
        "kind": "string",
        "origin": "canvas.drawCentredString",
        "page": 1,
        "x": 29.52,
        "y": 282.0
      },
      {
        "value": "WORKERS COMPENSATION",
        "kind": "string",
        "origin": "canvas.drawString",
        "page": 1,
        "x": 45.04,
        "y": 305.5
      },
      {
        "value": "AND EMPLOYERS' LIABILITY",
        "kind": "string",
        "origin": "canvas.drawString",
        "page": 1,
        "x": 45.04,
        "y": 295.5
      },
      {
        "value": "ANY PROPRIETOR/PARTNER/EXECUTIVE",
        "kind": "string",
        "origin": "canvas.drawString",
        "page": 1,
        "x": 45.04,
        "y": 284.5
      },
      {
        "value": "OFFICER/MEMBER EXCLUDED?",
        "kind": "string",
        "origin": "canvas.drawString",
        "page": 1,
        "x": 45.04,
        "y": 277.5
      },
      {
        "value": "N / A",
        "kind": "string",
        "origin": "canvas.drawString",
        "page": 1,
        "x": 142.0,
        "y": 277.5
      },
      {
        "value": "(Mandatory in NH)",
        "kind": "string",
        "origin": "canvas.drawString",
        "page": 1,
        "x": 45.04,
        "y": 271.0
      },
      {
        "value": "WC GLFS 2025 8820",
        "kind": "string",
        "origin": "canvas.drawString",
        "page": 1,
        "x": 200.56,
        "y": 285.0
      },
      {
        "value": "06/01/2025",
        "kind": "string",
        "origin": "canvas.drawString",
        "page": 1,
        "x": 286.96,
        "y": 285.0
      },
      {
        "value": "06/01/2026",
        "kind": "string",
        "origin": "canvas.drawString",
        "page": 1,
        "x": 338.8,
        "y": 285.0
      },
      {
        "value": "WC STATU-",
        "kind": "string",
        "origin": "canvas.drawString",
        "page": 1,
        "x": 388.64,
        "y": 308.5
      },
      {
        "value": "TORY LIMITS",
        "kind": "string",
        "origin": "canvas.drawString",
        "page": 1,
        "x": 388.64,
        "y": 303.0
      },
      {
        "value": "X",
        "kind": "string",
        "origin": "canvas.drawCentredString",
        "page": 1,
        "x": 510.688,
        "y": 304.6
      },
      {
        "value": "OTH-",
        "kind": "string",
        "origin": "canvas.drawString",
        "page": 1,
        "x": 546.16,
        "y": 308.5
      },
      {
        "value": "ER",
        "kind": "string",
        "origin": "canvas.drawString",
        "page": 1,
        "x": 546.16,
        "y": 303.0
      },
      {
        "value": "E.L. EACH ACCIDENT",
        "kind": "string",
        "origin": "acord_renderer.wrapped_text",
        "page": 1,
        "x": 388.64,
        "y": 493.0
      },
      {
        "value": "E.L. EACH ACCIDENT",
        "kind": "string",
        "origin": "reportlab.paragraph",
        "page": 1,
        "x": 388.64,
        "y": 292.675
      },
      {
        "value": "E.L. DISEASE - EA EMPLOYEE",
        "kind": "string",
        "origin": "acord_renderer.wrapped_text",
        "page": 1,
        "x": 388.64,
        "y": 505.0
      },
      {
        "value": "E.L. DISEASE - EA EMPLOYEE",
        "kind": "string",
        "origin": "reportlab.paragraph",
        "page": 1,
        "x": 388.64,
        "y": 280.675
      },
      {
        "value": "E.L. DISEASE - POLICY LIMIT",
        "kind": "string",
        "origin": "acord_renderer.wrapped_text",
        "page": 1,
        "x": 388.64,
        "y": 517.0
      },
      {
        "value": "E.L. DISEASE - POLICY LIMIT",
        "kind": "string",
        "origin": "reportlab.paragraph",
        "page": 1,
        "x": 388.64,
        "y": 268.675
      },
      {
        "value": "DESCRIPTION OF OPERATIONS / LOCATIONS / VEHICLES  (ACORD 101, Additional Remarks Schedule, may be attached if more space is required)",
        "kind": "string",
        "origin": "canvas.drawString",
        "page": 1,
        "x": 22.0,
        "y": 246.25
      },
      {
        "value": "RE: Regional trucking and freight logistics \u2014 LTL and FTL general freight, warehousing and distribution services across the Midwest and Mid-Atlantic corridors\nLocations: Corporate Headquarters & Main Terminal - 1200 Nationwide Boulevard, Columbus, OH 43215; Rickenbacker Air Hub - 2500 Norton Road, Columbus, OH 43217; Cleveland Distribution Center - 6000 Rockside Woods Boulevard, Independence, OH 44131\nQuantum Realty Management Inc. is included as Additional Insured as required by written contract. 30 days notice of cancellation will be provided.",
        "kind": "string",
        "origin": "acord_renderer.wrapped_text",
        "page": 1,
        "x": 22.0,
        "y": 554.0
      },
      {
        "value": "RE: Regional trucking and freight logistics \u2014 LTL and FTL general freight, warehousing and distribution services across the Midwest and Mid-Atlantic corridors",
        "kind": "string",
        "origin": "reportlab.paragraph.frag",
        "page": 1,
        "x": 22.0,
        "y": 200.0
      },
      {
        "value": "Locations: Corporate Headquarters & Main Terminal - 1200 Nationwide Boulevard, Columbus, OH 43215; Rickenbacker Air Hub - 2500 Norton Road, Columbus,",
        "kind": "string",
        "origin": "reportlab.paragraph.frag",
        "page": 1,
        "x": 22.0,
        "y": 200.0
      },
      {
        "value": "OH 43217; Cleveland Distribution Center - 6000 Rockside Woods Boulevard, Independence, OH 44131 Quantum Realty Management Inc. is included as Additional",
        "kind": "string",
        "origin": "reportlab.paragraph.frag",
        "page": 1,
        "x": 22.0,
        "y": 200.0
      },
      {
        "value": "Insured as required by written contract. 30 days notice of cancellation will be provided.",
        "kind": "string",
        "origin": "reportlab.paragraph.frag",
        "page": 1,
        "x": 22.0,
        "y": 200.0
      },
      {
        "value": "CERTIFICATE HOLDER",
        "kind": "string",
        "origin": "canvas.drawString",
        "page": 1,
        "x": 22.0,
        "y": 179.0
      },
      {
        "value": "CANCELLATION",
        "kind": "string",
        "origin": "canvas.drawString",
        "page": 1,
        "x": 310.0,
        "y": 179.0
      },
      {
        "value": "Quantum Realty Management Inc.",
        "kind": "string",
        "origin": "canvas.drawString",
        "page": 1,
        "x": 22.0,
        "y": 163.0
      },
      {
        "value": "5158 Summit Avenue",
        "kind": "string",
        "origin": "canvas.drawString",
        "page": 1,
        "x": 22.0,
        "y": 153.0
      },
      {
        "value": "Little Rock, AR 72201",
        "kind": "string",
        "origin": "canvas.drawString",
        "page": 1,
        "x": 22.0,
        "y": 143.0
      },
      {
        "value": "SHOULD ANY OF THE ABOVE DESCRIBED POLICIES BE CANCELLED BEFORE THE EXPIRATION DATE THEREOF, NOTICE WILL BE DELIVERED IN ACCORDANCE WITH THE POLICY PROVISIONS.",
        "kind": "string",
        "origin": "acord_renderer.wrapped_text",
        "page": 1,
        "x": 310.0,
        "y": 620.0
      },
      {
        "value": "SHOULD ANY OF THE ABOVE DESCRIBED POLICIES BE CANCELLED BEFORE THE EXPIRATION DATE THEREOF, NOTICE WILL BE DELIVERED IN ACCORDANCE WITH THE POLICY PROVISIONS.",
        "kind": "string",
        "origin": "reportlab.paragraph",
        "page": 1,
        "x": 310.0,
        "y": 148.0
      },
      {
        "value": "AUTHORIZED REPRESENTATIVE",
        "kind": "string",
        "origin": "canvas.drawString",
        "page": 1,
        "x": 310.0,
        "y": 121.0
      },
      {
        "value": "Margaret Sullivan",
        "kind": "string",
        "origin": "canvas.drawString",
        "page": 1,
        "x": 310.0,
        "y": 113.0
      },
      {
        "value": "ACORD 25 (2016/03)",
        "kind": "string",
        "origin": "canvas.drawString",
        "page": 1,
        "x": 18.0,
        "y": 15.5
      },
      {
        "value": "\u00a9 1988-2016 ACORD CORPORATION. All rights reserved.",
        "kind": "string",
        "origin": "canvas.drawRightString",
        "page": 1,
        "x": 594.0,
        "y": 15.5
      },
      {
        "value": "The ACORD name and logo are registered marks of ACORD",
        "kind": "string",
        "origin": "canvas.drawCentredString",
        "page": 1,
        "x": 306.0,
        "y": 2.5
      },
      {
        "value": "Page 1 of 1",
        "kind": "string",
        "origin": "canvas.drawCentredString",
        "page": 1,
        "x": 306.0,
        "y": 15.5
      },
      {
        "value": "M. Johnson",
        "kind": "string",
        "origin": "overlay.p56_handwritten",
        "page": 1,
        "x": 0.0,
        "y": 0.0
      },
      {
        "value": "6/18/2025",
        "kind": "string",
        "origin": "overlay.p56_handwritten",
        "page": 1,
        "x": 0.0,
        "y": 0.0
      },
      {
        "value": "Need docs",
        "kind": "string",
        "origin": "overlay.p56_handwritten",
        "page": 1,
        "x": 0.0,
        "y": 0.0
      }
    ],
    "corrupted_view": {
      "transforms_applied": [
        "p42_font_corrupt"
      ],
      "strings": [
        "ACORD",
        "\u00ae",
        "CERTIFICATE OF LIABILITY INSURANCE",
        "DATE (MM/DD/YYYY)",
        "\ufffd3/16/2\ufffd26",
        "THIS CERTIFICATE IS ISSUED AS A MATTER OF INFORMATION ONLY AND CONFERS NO RIGHTS UPON THE CERTIFICATE HOLDER. THIS CERTIFICATE DOES NOT AFFIRMATIVELY OR NEGATIVELY AMEND, EXTEND OR ALTER THE COVERAGE AFFORDED BY THE POLICIES BELOW. THIS CERTIFICATE OF INSURANCE DOES NOT CONSTITUTE A CONTRACT BETWEEN THE ISSUING INSURER(S), AUTHORIZED REPRESENTATIVE OR PRODUCER, AND THE CERTIFICATE HOLDER.",
        "IMPORTANT:",
        "If the certificate holder is an ADDITIONAL INSURED, the policy(ies) must have ADDITIONAL INSURED provisions or be endorsed. If SUBROGATION IS WAIVED, subject to the terms and conditions of the policy, certain policies may require an endorsement. A statement on this certificate does not confer rights to the certificate holder in lieu of such endorsement(s).",
        "PRODUCER",
        "Transportation Insurance Specialists",
        "David Reinhardt",
        "41 South High Street, Suite 28\ufffd\ufffd",
        "Columbus, OH 4321\ufffd",
        "Phone: (614) \ufffd\ufffd\ufffd-\ufffd493  Fax: (614) 26\ufffd-6839",
        "E-Mail: dreinhardt@tisgroup.com",
        "INSURED",
        "Great Lakes Freight Systems, Incorporated",
        "12\ufffd\ufffd Nationwide Blvd.",
        "CONTACT NAME:",
        "PHONE (A/C, No, Ext):",
        "(614) \ufffd\ufffd\ufffd-\ufffd493",
        "FAX (A/C, No):",
        "(614) 26\ufffd-6839",
        "E-MAIL ADDRESS:",
        "dreinhardt@tisgroup.com",
        "INSURER(S) AFFORDING COVERAGE",
        "NAIC #",
        "INSURER A:",
        "Ohio Bureau of Workers' Compensation",
        "21\ufffd\ufffd8",
        "INSURER B:",
        "Standard Insurance Company",
        "21\ufffd93",
        "INSURER C:",
        "21\ufffd88",
        "INSURER D:",
        "212\ufffd6",
        "INSURER E:",
        "INSURER F:",
        "COVERAGES",
        "CERTIFICATE NUMBER:",
        "REVISION NUMBER:",
        "THIS IS TO CERTIFY THAT THE POLICIES OF INSURANCE LISTED BELOW HAVE BEEN ISSUED TO THE INSURED NAMED ABOVE FOR THE POLICY PERIOD INDICATED. NOTWITHSTANDING ANY REQUIREMENT, TERM OR CONDITION OF ANY CONTRACT OR OTHER DOCUMENT WITH RESPECT TO WHICH THIS CERTIFICATE MAY BE ISSUED OR MAY PERTAIN, THE INSURANCE AFFORDED BY THE POLICIES DESCRIBED HEREIN IS SUBJECT TO ALL THE TERMS, EXCLUSIONS AND CONDITIONS OF SUCH POLICIES. LIMITS SHOWN MAY HAVE BEEN REDUCED BY PAID CLAIMS.",
        "INSR",
        "LTR",
        "TYPE OF INSURANCE",
        "ADDL  SUBR",
        "INSD  WVD",
        "POLICY NUMBER",
        "POLICY EFF",
        "(MM/DD/YYYY)",
        "POLICY EXP",
        "LIMITS",
        "B",
        "COMMERCIAL GENERAL LIABILITY",
        "CLAIMS-MADE",
        "X",
        "OCCUR",
        "GEN'L AGGREGATE LIMIT APPLIES PER:",
        "POLICY",
        "PRO-JECT",
        "LOC",
        "Y",
        "gl GLFS 2\ufffd2\ufffd 8821",
        "\ufffd6/\ufffd1/2\ufffd2\ufffd",
        "\ufffd6/\ufffd1/2\ufffd26",
        "EACH OCCURRENCE",
        "$ 2,\ufffd\ufffd\ufffd,\ufffd\ufffd\ufffd",
        "DAMAGE TO RENTED PREMISES (Ea occurrence)",
        "$ \ufffd\ufffd\ufffd,\ufffd\ufffd\ufffd",
        "MED EXP (Any one person)",
        "$ \ufffd,\ufffd\ufffd\ufffd",
        "PERSONAL & ADV INJURY",
        "GENERAL AGGREGATE",
        "$ 4,\ufffd\ufffd\ufffd,\ufffd\ufffd\ufffd",
        "PRODUCTS - COMP/OP AGG",
        "$",
        "C",
        "AUTOMOBILE LIABILITY",
        "ANY AUTO",
        "OWNED AUTOS ONLY",
        "SCHEDULED AUTOS",
        "HIRED AUTOS ONLY",
        "NON-OWNED AUTOS ONLY",
        "CAGLFS2\ufffd2\ufffd8822",
        "COMBINED SINGLE LIMIT (Ea accident)",
        "$ \ufffd,\ufffd\ufffd\ufffd,\ufffd\ufffd\ufffd",
        "BODILY INJURY (Per person)",
        "BODILY INJURY (Per accident)",
        "PROPERTY DAMAGE (Per accident)",
        "D",
        "UMBRELLA LIAB",
        "DED    RETENTION $",
        "SIC CU\ufffd2\ufffd4\ufffd4",
        "$ 1\ufffd,\ufffd\ufffd\ufffd,\ufffd\ufffd\ufffd",
        "AGGREGATE",
        "A",
        "WORKERS COMPENSATION",
        "AND EMPLOYERS' LIABILITY",
        "ANY PROPRIETOR/PARTNER/EXECUTIVE",
        "OFFICER/MEMBER EXCLUDED?",
        "N / A",
        "(Mandatory in NH)",
        "WC GLFS 2\ufffd2\ufffd 882\ufffd",
        "WC STATU-",
        "TORY LIMITS",
        "OTH-",
        "ER",
        "E.L. EACH ACCIDENT",
        "E.L. DISEASE - EA EMPLOYEE",
        "E.L. DISEASE - POLICY LIMIT",
        "DESCRIPTION OF OPERATIONS / LOCATIONS / VEHICLES  (ACORD 1\ufffd1, Additional Remarks Schedule, may be attached if more space is required)",
        "RE: Regional trucking and freight logistics \u2014 LTL and FTL general freight, warehousing and distribution services across the Midwest and Mid-Atlantic corridors\nLocations: Corporate Headquarters & Main Terminal - 12\ufffd\ufffd Nationwide Boulevard, Columbus, OH 4321\ufffd; Rickenbacker Air Hub - 2\ufffd\ufffd\ufffd Norton Road, Columbus, OH 4321\ufffd; Cleveland Distribution Center - 6\ufffd\ufffd\ufffd Rockside Woods Boulevard, Independence, OH 44131\nQuantum Realty Management Inc. is included as Additional Insured as required by written contract. 3\ufffd days notice of cancellation will be provided.",
        "RE: Regional trucking and freight logistics \u2014 LTL and FTL general freight, warehousing and distribution services across the Midwest and Mid-Atlantic corridors",
        "Locations: Corporate Headquarters & Main Terminal - 12\ufffd\ufffd Nationwide Boulevard, Columbus, OH 4321\ufffd; Rickenbacker Air Hub - 2\ufffd\ufffd\ufffd Norton Road, Columbus,",
        "OH 4321\ufffd; Cleveland Distribution Center - 6\ufffd\ufffd\ufffd Rockside Woods Boulevard, Independence, OH 44131 Quantum Realty Management Inc. is included as Additional",
        "Insured as required by written contract. 3\ufffd days notice of cancellation will be provided.",
        "CERTIFICATE HOLDER",
        "CANCELLATION",
        "Quantum Realty Management Inc.",
        "\ufffd1\ufffd8 Summit Avenue",
        "Little Rock, AR \ufffd22\ufffd1",
        "SHOULD ANY OF THE ABOVE DESCRIBED POLICIES BE CANCELLED BEFORE THE EXPIRATION DATE THEREOF, NOTICE WILL BE DELIVERED IN ACCORDANCE WITH THE POLICY PROVISIONS.",
        "AUTHORIZED REPRESENTATIVE",
        "Margaret Sullivan",
        "ACORD 2\ufffd (2\ufffd16/\ufffd3)",
        "\u00a9 1988-2\ufffd16 ACORD CORPORATION. All rights reserved.",
        "The ACORD name and logo are registered marks of ACORD",
        "Page 1 of 1",
        "M. Johnson",
        "6/18/2\ufffd2\ufffd",
        "Need docs"
      ],
      "numbers": [
        4321,
        614,
        493,
        -6839,
        212,
        8821,
        8822,
        882,
        44131,
        1988
      ],
      "tokens": [
        "acord",
        "certificate",
        "of",
        "liability",
        "insurance",
        "date",
        "mm",
        "dd",
        "yyyy",
        "16",
        "26",
        "this",
        "is",
        "issued",
        "as",
        "matter",
        "information",
        "only",
        "and",
        "confers",
        "no",
        "rights",
        "upon",
        "the",
        "holder",
        "does",
        "not",
        "affirmatively",
        "or",
        "negatively",
        "amend",
        "extend",
        "alter",
        "coverage",
        "afforded",
        "by",
        "policies",
        "below",
        "constitute",
        "contract",
        "between",
        "issuing",
        "insurer",
        "authorized",
        "representative",
        "producer",
        "important",
        "if",
        "an",
        "additional",
        "insured",
        "policy",
        "ies",
        "must",
        "have",
        "provisions",
        "be",
        "endorsed",
        "subrogation",
        "waived",
        "subject",
        "to",
        "terms",
        "conditions",
        "certain",
        "may",
        "require",
        "endorsement",
        "statement",
        "on",
        "confer",
        "in",
        "lieu",
        "such",
        "transportation",
        "specialists",
        "david",
        "reinhardt",
        "41",
        "south",
        "high",
        "street",
        "suite",
        "28",
        "columbus",
        "oh",
        "4321",
        "phone",
        "614",
        "493",
        "fax",
        "6839",
        "e-mail",
        "dreinhardt",
        "tisgroup.com",
        "great",
        "lakes",
        "freight",
        "systems",
        "incorporated",
        "12",
        "nationwide",
        "blvd",
        "contact",
        "name",
        "ext",
        "address",
        "affording",
        "naic",
        "ohio",
        "bureau",
        "workers",
        "compensation",
        "21",
        "standard",
        "company",
        "93",
        "88",
        "212",
        "coverages",
        "number",
        "revision",
        "certify",
        "that",
        "listed",
        "been",
        "named",
        "above",
        "for",
        "period",
        "indicated",
        "notwithstanding",
        "any",
        "requirement",
        "term",
        "condition",
        "other",
        "document",
        "with",
        "respect",
        "which",
        "pertain",
        "described",
        "herein",
        "all",
        "exclusions",
        "limits",
        "shown",
        "reduced",
        "paid",
        "claims",
        "insr",
        "ltr",
        "type",
        "addl",
        "subr",
        "insd",
        "wvd",
        "eff",
        "exp",
        "commercial",
        "general",
        "claims-made",
        "occur",
        "gen",
        "aggregate",
        "limit",
        "applies",
        "per",
        "pro-ject",
        "loc",
        "gl",
        "glfs",
        "8821",
        "each",
        "occurrence",
        "damage",
        "rented",
        "premises",
        "ea",
        "med",
        "one",
        "person",
        "personal",
        "adv",
        "injury",
        "products",
        "comp",
        "op",
        "agg",
        "automobile",
        "auto",
        "owned",
        "autos",
        "scheduled",
        "hired",
        "non-owned",
        "caglfs2",
        "8822",
        "combined",
        "single",
        "accident",
        "bodily",
        "property",
        "umbrella",
        "liab",
        "ded",
        "retention",
        "sic",
        "cu",
        "employers",
        "proprietor",
        "partner",
        "executive",
        "officer",
        "member",
        "excluded",
        "mandatory",
        "nh",
        "wc",
        "882",
        "statu",
        "tory",
        "oth",
        "er",
        "e.l",
        "disease",
        "employee",
        "description",
        "operations",
        "locations",
        "vehicles",
        "remarks",
        "schedule",
        "attached",
        "more",
        "space",
        "required",
        "re",
        "regional",
        "trucking",
        "logistics",
        "ltl",
        "ftl",
        "warehousing",
        "distribution",
        "services",
        "across",
        "midwest",
        "mid-atlantic",
        "corridors",
        "corporate",
        "headquarters",
        "main",
        "terminal",
        "boulevard",
        "rickenbacker",
        "air",
        "hub",
        "norton",
        "road",
        "cleveland",
        "center",
        "rockside",
        "woods",
        "independence",
        "44131",
        "quantum",
        "realty",
        "management",
        "inc",
        "included",
        "written",
        "days",
        "notice",
        "cancellation",
        "will",
        "provided",
        "summit",
        "avenue",
        "little",
        "rock",
        "ar",
        "22",
        "should",
        "cancelled",
        "before",
        "expiration",
        "thereof",
        "delivered",
        "accordance",
        "margaret",
        "sullivan",
        "1988-2",
        "corporation",
        "reserved",
        "logo",
        "are",
        "registered",
        "marks",
        "page",
        "johnson",
        "18",
        "need",
        "docs"
      ],
      "rendered_text": "ACORD\n\u00ae\nCERTIFICATE OF LIABILITY INSURANCE\nDATE (MM/DD/YYYY)\n\ufffd3/16/2\ufffd26\nTHIS CERTIFICATE IS ISSUED AS A MATTER OF INFORMATION ONLY AND CONFERS NO RIGHTS UPON THE CERTIFICATE HOLDER. THIS CERTIFICATE DOES NOT AFFIRMATIVELY OR NEGATIVELY AMEND, EXTEND OR ALTER THE COVERAGE AFFORDED BY THE POLICIES BELOW. THIS CERTIFICATE OF INSURANCE DOES NOT CONSTITUTE A CONTRACT BETWEEN THE ISSUING INSURER(S), AUTHORIZED REPRESENTATIVE OR PRODUCER, AND THE CERTIFICATE HOLDER.\nIMPORTANT:\nIf the certificate holder is an ADDITIONAL INSURED, the policy(ies) must have ADDITIONAL INSURED provisions or be endorsed. If SUBROGATION IS WAIVED, subject to the terms and conditions of the policy, certain policies may require an endorsement. A statement on this certificate does not confer rights to the certificate holder in lieu of such endorsement(s).\nPRODUCER\nTransportation Insurance Specialists\nDavid Reinhardt\n41 South High Street, Suite 28\ufffd\ufffd\nColumbus, OH 4321\ufffd\nPhone: (614) \ufffd\ufffd\ufffd-\ufffd493  Fax: (614) 26\ufffd-6839\nE-Mail: dreinhardt@tisgroup.com\nINSURED\nGreat Lakes Freight Systems, Incorporated\n12\ufffd\ufffd Nationwide Blvd.\nCONTACT NAME:\nPHONE (A/C, No, Ext):\n(614) \ufffd\ufffd\ufffd-\ufffd493\nFAX (A/C, No):\n(614) 26\ufffd-6839\nE-MAIL ADDRESS:\ndreinhardt@tisgroup.com\nINSURER(S) AFFORDING COVERAGE\nNAIC #\nINSURER A:\nOhio Bureau of Workers' Compensation\n21\ufffd\ufffd8\nINSURER B:\nStandard Insurance Company\n21\ufffd93\nINSURER C:\n21\ufffd88\nINSURER D:\n212\ufffd6\nINSURER E:\nINSURER F:\nCOVERAGES\nCERTIFICATE NUMBER:\nREVISION NUMBER:\nTHIS IS TO CERTIFY THAT THE POLICIES OF INSURANCE LISTED BELOW HAVE BEEN ISSUED TO THE INSURED NAMED ABOVE FOR THE POLICY PERIOD INDICATED. NOTWITHSTANDING ANY REQUIREMENT, TERM OR CONDITION OF ANY CONTRACT OR OTHER DOCUMENT WITH RESPECT TO WHICH THIS CERTIFICATE MAY BE ISSUED OR MAY PERTAIN, THE INSURANCE AFFORDED BY THE POLICIES DESCRIBED HEREIN IS SUBJECT TO ALL THE TERMS, EXCLUSIONS AND CONDITIONS OF SUCH POLICIES. LIMITS SHOWN MAY HAVE BEEN REDUCED BY PAID CLAIMS.\nINSR\nLTR\nTYPE OF INSURANCE\nADDL  SUBR\nINSD  WVD\nPOLICY NUMBER\nPOLICY EFF\n(MM/DD/YYYY)\nPOLICY EXP\nLIMITS\nB\nCOMMERCIAL GENERAL LIABILITY\nCLAIMS-MADE\nX\nOCCUR\nGEN'L AGGREGATE LIMIT APPLIES PER:\nPOLICY\nPRO-JECT\nLOC\nY\ngl GLFS 2\ufffd2\ufffd 8821\n\ufffd6/\ufffd1/2\ufffd2\ufffd\n\ufffd6/\ufffd1/2\ufffd26\nEACH OCCURRENCE\n$ 2,\ufffd\ufffd\ufffd,\ufffd\ufffd\ufffd\nDAMAGE TO RENTED PREMISES (Ea occurrence)\n$ \ufffd\ufffd\ufffd,\ufffd\ufffd\ufffd\nMED EXP (Any one person)\n$ \ufffd,\ufffd\ufffd\ufffd\nPERSONAL & ADV INJURY\nGENERAL AGGREGATE\n$ 4,\ufffd\ufffd\ufffd,\ufffd\ufffd\ufffd\nPRODUCTS - COMP/OP AGG\n$\nC\nAUTOMOBILE LIABILITY\nANY AUTO\nOWNED AUTOS ONLY\nSCHEDULED AUTOS\nHIRED AUTOS ONLY\nNON-OWNED AUTOS ONLY\nCAGLFS2\ufffd2\ufffd8822\nCOMBINED SINGLE LIMIT (Ea accident)\n$ \ufffd,\ufffd\ufffd\ufffd,\ufffd\ufffd\ufffd\nBODILY INJURY (Per person)\nBODILY INJURY (Per accident)\nPROPERTY DAMAGE (Per accident)\nD\nUMBRELLA LIAB\nDED    RETENTION $\nSIC CU\ufffd2\ufffd4\ufffd4\n$ 1\ufffd,\ufffd\ufffd\ufffd,\ufffd\ufffd\ufffd\nAGGREGATE\nA\nWORKERS COMPENSATION\nAND EMPLOYERS' LIABILITY\nANY PROPRIETOR/PARTNER/EXECUTIVE\nOFFICER/MEMBER EXCLUDED?\nN / A\n(Mandatory in NH)\nWC GLFS 2\ufffd2\ufffd 882\ufffd\nWC STATU-\nTORY LIMITS\nOTH-\nER\nE.L. EACH ACCIDENT\nE.L. DISEASE - EA EMPLOYEE\nE.L. DISEASE - POLICY LIMIT\nDESCRIPTION OF OPERATIONS / LOCATIONS / VEHICLES  (ACORD 1\ufffd1, Additional Remarks Schedule, may be attached if more space is required)\nRE: Regional trucking and freight logistics \u2014 LTL and FTL general freight, warehousing and distribution services across the Midwest and Mid-Atlantic corridors\nLocations: Corporate Headquarters & Main Terminal - 12\ufffd\ufffd Nationwide Boulevard, Columbus, OH 4321\ufffd; Rickenbacker Air Hub - 2\ufffd\ufffd\ufffd Norton Road, Columbus, OH 4321\ufffd; Cleveland Distribution Center - 6\ufffd\ufffd\ufffd Rockside Woods Boulevard, Independence, OH 44131\nQuantum Realty Management Inc. is included as Additional Insured as required by written contract. 3\ufffd days notice of cancellation will be provided.\nRE: Regional trucking and freight logistics \u2014 LTL and FTL general freight, warehousing and distribution services across the Midwest and Mid-Atlantic corridors\nLocations: Corporate Headquarters & Main Terminal - 12\ufffd\ufffd Nationwide Boulevard, Columbus, OH 4321\ufffd; Rickenbacker Air Hub - 2\ufffd\ufffd\ufffd Norton Road, Columbus,\nOH 4321\ufffd; Cleveland Distribution Center - 6\ufffd\ufffd\ufffd Rockside Woods Boulevard, Independence, OH 44131 Quantum Realty Management Inc. is included as Additional\nInsured as required by written contract. 3\ufffd days notice of cancellation will be provided.\nCERTIFICATE HOLDER\nCANCELLATION\nQuantum Realty Management Inc.\n\ufffd1\ufffd8 Summit Avenue\nLittle Rock, AR \ufffd22\ufffd1\nSHOULD ANY OF THE ABOVE DESCRIBED POLICIES BE CANCELLED BEFORE THE EXPIRATION DATE THEREOF, NOTICE WILL BE DELIVERED IN ACCORDANCE WITH THE POLICY PROVISIONS.\nAUTHORIZED REPRESENTATIVE\nMargaret Sullivan\nACORD 2\ufffd (2\ufffd16/\ufffd3)\n\u00a9 1988-2\ufffd16 ACORD CORPORATION. All rights reserved.\nThe ACORD name and logo are registered marks of ACORD\nPage 1 of 1\nM. Johnson\n6/18/2\ufffd2\ufffd\nNeed docs"
    },
    "page_count": 1
  }
}